channels_valkey/__init__.py
channels_valkey/core.py
channels_valkey/pubsub.py
channels_valkey/serializers.py
channels_valkey/utils.py
channels_valkey-0.3.0.dist-info/METADATA
channels_valkey-0.3.0.dist-info/WHEEL
channels_valkey-0.3.0.dist-info/licenses/LICENSE
channels_valkey-0.3.0.dist-info/RECORD
