Metadata-Version: 2.4
Name: channels-valkey
Version: 0.3.0
Summary: Valkey-backed ASGI channel layer implementation
Project-URL: Homepage, https://github.com/django-utils/channels-valkey
Project-URL: Source, https://github.com/django-utils/channels-valkey
Project-URL: Issues, https://github.com/django-utils/channels-valkey/issues
License-File: LICENSE
Requires-Python: >=3.9
Requires-Dist: asgiref>=3.9.1
Requires-Dist: channels>=4.2.2
Requires-Dist: msgpack>=1.1.0
Requires-Dist: valkey>=6.0.0
Provides-Extra: cryptography
Requires-Dist: cryptography>=43.0.1; extra == 'cryptography'
